stimline_idex/__init__.py
stimline_idex/logging.py
stimline_idex/v1/__init__.py
stimline_idex/v1/api/__init__.py
stimline_idex/v1/api/api.py
stimline_idex/v1/api/auth.py
stimline_idex/v1/api/client.py
stimline_idex/v1/api/modules/__init__.py
stimline_idex/v1/api/modules/change_logs.py
stimline_idex/v1/api/modules/channels.py
stimline_idex/v1/api/modules/coils.py
stimline_idex/v1/api/modules/customers.py
stimline_idex/v1/api/modules/fields.py
stimline_idex/v1/api/modules/installations.py
stimline_idex/v1/api/modules/logs.py
stimline_idex/v1/api/modules/reels.py
stimline_idex/v1/api/modules/runs.py
stimline_idex/v1/api/modules/soe.py
stimline_idex/v1/api/modules/surveys.py
stimline_idex/v1/api/modules/tests.py
stimline_idex/v1/api/modules/unit_active_wellbore.py
stimline_idex/v1/api/modules/units.py
stimline_idex/v1/api/modules/uoms.py
stimline_idex/v1/api/modules/utils.py
stimline_idex/v1/api/modules/wellbore_history.py
stimline_idex/v1/api/modules/wellbore_live_status.py
stimline_idex/v1/api/modules/wellbores.py
stimline_idex/v1/api/modules/wells.py
stimline_idex/v1/data_schemas/__init__.py
stimline_idex/v1/data_schemas/assets.py
stimline_idex/v1/data_schemas/auth.py
stimline_idex/v1/data_schemas/base.py
stimline_idex/v1/data_schemas/change_log.py
stimline_idex/v1/data_schemas/channel_data.py
stimline_idex/v1/data_schemas/events/__init__.py
stimline_idex/v1/data_schemas/events/events.py
stimline_idex/v1/data_schemas/events/job_plans.py
stimline_idex/v1/data_schemas/events/soe.py
stimline_idex/v1/data_schemas/events/tests.py
stimline_idex/v1/data_schemas/uoms.py
stimline_idex-0.4.1.dist-info/LICENSE
stimline_idex-0.4.1.dist-info/METADATA
stimline_idex-0.4.1.dist-info/WHEEL
stimline_idex-0.4.1.dist-info/RECORD
