Metadata-Version: 2.1
Name: stimline-idex
Version: 0.4.1
Summary: API Wrapper for the Stimline IDEX collaboration platform software used for well intervention.
Author: Marcus Risanger
Author-email: 69350948+MarcusRisanger@users.noreply.github.com
Requires-Python: >=3.9,<4.0
Classifier: Programming Language :: Python :: 3
Classifier: Programming Language :: Python :: 3.9
Classifier: Programming Language :: Python :: 3.10
Classifier: Programming Language :: Python :: 3.11
Classifier: Programming Language :: Python :: 3.12
Requires-Dist: pydantic (>=2.8.2,<3.0.0)
Requires-Dist: requests (>=2.32.3,<3.0.0)
